LICENSE
MANIFEST.in
README.md
quicktest.py
settings_test.py
setup.py
django_odnoklassniki_users.egg-info/PKG-INFO
django_odnoklassniki_users.egg-info/SOURCES.txt
django_odnoklassniki_users.egg-info/dependency_links.txt
django_odnoklassniki_users.egg-info/not-zip-safe
django_odnoklassniki_users.egg-info/requires.txt
django_odnoklassniki_users.egg-info/top_level.txt
odnoklassniki_users/__init__.py
odnoklassniki_users/__init__.pyc
odnoklassniki_users/admin.py
odnoklassniki_users/admin.pyc
odnoklassniki_users/factories.py
odnoklassniki_users/factories.pyc
odnoklassniki_users/models.py
odnoklassniki_users/models.pyc
odnoklassniki_users/signals.py
odnoklassniki_users/signals.pyc
odnoklassniki_users/tasks.py
odnoklassniki_users/tasks.pyc
odnoklassniki_users/tests.py
odnoklassniki_users/tests.pyc
odnoklassniki_users/migrations/0001_initial.py
odnoklassniki_users/migrations/0001_initial.pyc
odnoklassniki_users/migrations/__init__.py
odnoklassniki_users/migrations/__init__.pyc