Metadata-Version: 1.1
Name: django-odnoklassniki-users
Version: 0.2.1
Summary: Django implementation for odnoklassniki API Users
Home-page: https://github.com/ramusus/django-odnoklassniki-users
Author: ramusus
Author-email: ramusus@gmail.com
License: BSD
Download-URL: http://pypi.python.org/pypi/django-odnoklassniki-users
Platform: UNKNOWN
Classifier: Development Status :: 4 - Beta
Classifier: Environment :: Web Environment
Classifier: Intended Audience :: Developers
Classifier: License :: OSI Approved :: BSD License
Classifier: Operating System :: OS Independent
Classifier: Programming Language :: Python
Classifier: Topic :: Software Development :: Libraries :: Python Modules
